{
    "shadow": {
        "elements": [
            {
                "name": "layoutScope",
                "selector": {
                    "css": "div.flex"
                },
                "elements": [
                    {
                        "name": "navbar",
                        "type": "lwr-project/navbar",
                        "selector": {
                            "css": "orionlabs-navbar"
                        },
                        "public": true
                    },
                    {
                        "name": "footer",
                        "selector": {
                            "css": "orionlabs-footer"
                        },
                        "public": true
                    }
                ]
            }
        ]
    }
}
